async_connect/__init__.py
async_connect/artist.py
async_connect/client.py
async_connect/errors.py
async_connect/http.py
async_connect/iterators.py
async_connect/playlist.py
async_connect/release.py
async_connect/track.py
async_connect/utils.py
async_connect.py-0.2.1.dist-info/DESCRIPTION.rst
async_connect.py-0.2.1.dist-info/METADATA
async_connect.py-0.2.1.dist-info/RECORD
async_connect.py-0.2.1.dist-info/WHEEL
async_connect.py-0.2.1.dist-info/metadata.json
async_connect.py-0.2.1.dist-info/top_level.txt
tests/__init__.py
tests/test_get_all_catalog.py
tests/test_get_catalog.py
tests/test_search.py
