Metadata-Version: 2.0
Name: async-connect.py
Version: 0.2.1
Summary: Asynchronous version of connect.py
Home-page: https://github.com/GiovanniMCMXCIX/async-connect.py
Author: GiovanniMCMXCIX
Author-email: irimea.giovani.9@gmail.com
License: MIT
Platform: UNKNOWN
Classifier: Development Status :: 4 - Beta
Classifier: License :: OSI Approved :: MIT License
Classifier: Intended Audience :: Developers
Classifier: Natural Language :: English
Classifier: Operating System :: OS Independent
Classifier: Programming Language :: Python :: 3 :: Only
Classifier: Programming Language :: Python :: 3.6
Classifier: Topic :: Internet
Classifier: Topic :: Software Development :: Libraries
Classifier: Topic :: Software Development :: Libraries :: Python Modules
Classifier: Topic :: Utilities
Requires-Python: >=3.6.2
Requires-Dist: aiohttp (>=2.3.1)
Provides-Extra: performance
Requires-Dist: uvloop (>=0.8.0); extra == 'performance'
Requires-Dist: ujson (>=1.35); extra == 'performance'
